Metadata-Version: 2.1
Name: sociolla
Version: 0.7
Summary: Scrap Sociolla
Home-page: https://github.com/faridrizqi46/Sociolla
Author: Farid Rizqi
Author-email: faridrizqi46@gmail.com
License: MIT
Keywords: Sociolla,Scrap,Compas
Platform: UNKNOWN
Classifier: Development Status :: 4 - Beta
Classifier: Intended Audience :: Developers
Classifier: Topic :: Software Development :: Build Tools
Classifier: License :: OSI Approved :: MIT License
Classifier: Programming Language :: Python :: 3
Classifier: Operating System :: Unix
Classifier: Operating System :: MacOS :: MacOS X
Classifier: Operating System :: Microsoft :: Windows
License-File: LICENSE.txt
